<?xml version="1.0" encoding="UTF-8"?>

<FLOW VERSION="3.0" CLEANUP="true">
  <COMMENT></COMMENT>

  <!-- nodes -->

<INVOKE TIMEOUT="" SERVICE="pub.flow:savePipelineToFile" VALIDATE-IN="$none" VALIDATE-OUT="$none" DISABLED="true">
  <COMMENT></COMMENT>

  <!-- nodes -->

<MAP MODE="INPUT">
  <MAPTARGET>

<Values version="2.0">
  <record name="xml" javaclass="com.wm.util.Values">
    <value name="node_type">record</value>
    <value name="is_public">false</value>
    <value name="field_name">savePipelineToFileInput</value>
    <value name="field_type">record</value>
    <value name="field_dim">0</value>
    <value name="wrapper_type">IData</value>
    <value name="nillable">true</value>
    <value name="form_qualified">false</value>
    <value name="is_global">false</value>
    <array name="rec_fields" type="record" depth="1">
      <record javaclass="com.wm.util.Values">
        <value name="node_type">unknown</value>
        <value name="is_public">false</value>
        <value name="field_name">fileName</value>
        <value name="field_type">string</value>
        <value name="field_dim">0</value>
        <value name="nillable">true</value>
        <value name="form_qualified">false</value>
        <value name="is_global">false</value>
      </record>
    </array>
    <value name="modifiable">true</value>
  </record>
</Values>
</MAPTARGET>
  <MAPSOURCE>

<Values version="2.0">
  <record name="xml" javaclass="com.wm.util.Values">
    <value name="node_type">record</value>
    <value name="is_public">false</value>
    <value name="field_type">record</value>
    <value name="field_dim">0</value>
    <value name="wrapper_type">IData</value>
    <value name="nillable">true</value>
    <value name="form_qualified">false</value>
    <value name="is_global">false</value>
    <array name="rec_fields" type="record" depth="1">
    </array>
    <value name="modifiable">true</value>
  </record>
</Values>
</MAPSOURCE>

  <!-- nodes -->

<MAPSET NAME="Setter" OVERWRITE="true" VARIABLES="true" GLOBALVARIABLES="false" FIELD="/fileName;1;0">
  <DATA ENCODING="XMLValues" I18N="true">

<Values version="2.0">
  <value name="xml">GlanbiaInvoice1</value>
  <record name="type" javaclass="com.wm.util.Values">
    <value name="node_type">unknown</value>
    <value name="is_public">false</value>
    <value name="field_name">fileName</value>
    <value name="field_type">string</value>
    <value name="field_dim">0</value>
    <value name="nillable">true</value>
    <value name="form_qualified">false</value>
    <value name="is_global">false</value>
  </record>
</Values>
</DATA>
</MAPSET>
</MAP>

<MAP MODE="OUTPUT">
  <MAPTARGET>

<Values version="2.0">
  <record name="xml" javaclass="com.wm.util.Values">
    <value name="node_type">record</value>
    <value name="is_public">false</value>
    <value name="field_type">record</value>
    <value name="field_dim">0</value>
    <value name="wrapper_type">IData</value>
    <value name="nillable">true</value>
    <value name="form_qualified">false</value>
    <value name="is_global">false</value>
    <array name="rec_fields" type="record" depth="1">
      <record javaclass="com.wm.util.Values">
        <value name="node_type">unknown</value>
        <value name="is_public">false</value>
        <value name="field_name">fileName</value>
        <value name="field_type">string</value>
        <value name="field_dim">0</value>
        <value name="nillable">true</value>
        <value name="form_qualified">false</value>
        <value name="is_global">false</value>
      </record>
      <record javaclass="com.wm.util.Values">
        <value name="node_type">unknown</value>
        <value name="is_public">false</value>
        <value name="field_name">value</value>
        <value name="field_type">string</value>
        <value name="field_dim">0</value>
        <value name="nillable">true</value>
        <value name="form_qualified">false</value>
        <value name="is_global">false</value>
      </record>
      <record javaclass="com.wm.util.Values">
        <value name="node_type">unknown</value>
        <value name="is_public">false</value>
        <value name="field_name">pattern</value>
        <value name="field_type">string</value>
        <value name="field_dim">0</value>
        <value name="nillable">true</value>
        <value name="form_qualified">false</value>
        <value name="is_global">false</value>
      </record>
      <record javaclass="com.wm.util.Values">
        <value name="node_type">record</value>
        <value name="node_comment"></value>
        <record name="node_hints" javaclass="com.wm.util.Values">
          <value name="field_largerEditor">false</value>
          <value name="field_password">false</value>
        </record>
        <value name="is_public">false</value>
        <value name="field_name">INVOIC02</value>
        <value name="field_type">recref</value>
        <value name="field_dim">0</value>
        <value name="nillable">true</value>
        <value name="form_qualified">false</value>
        <value name="is_global">false</value>
        <value name="modifiable">true</value>
        <value name="rec_ref">PKIWmAriba.documents.IDoc:INVOIC02</value>
      </record>
      <record javaclass="com.wm.util.Values">
        <value name="node_type">record</value>
        <value name="node_comment"></value>
        <record name="node_hints" javaclass="com.wm.util.Values">
          <value name="field_largerEditor">false</value>
          <value name="field_password">false</value>
        </record>
        <value name="is_public">false</value>
        <value name="field_name">orderRequest</value>
        <value name="field_type">recref</value>
        <value name="field_dim">0</value>
        <value name="wrapper_type">IData</value>
        <value name="nillable">true</value>
        <value name="form_qualified">false</value>
        <value name="is_global">false</value>
        <value name="modifiable">true</value>
        <value name="rec_ref">PKIWmAriba.documents.doc_cXML:cXML</value>
      </record>
    </array>
    <value name="modifiable">true</value>
  </record>
</Values>
</MAPTARGET>
  <MAPSOURCE>

<Values version="2.0">
  <record name="xml" javaclass="com.wm.util.Values">
    <value name="node_type">record</value>
    <value name="is_public">false</value>
    <value name="field_type">record</value>
    <value name="field_dim">0</value>
    <value name="wrapper_type">IData</value>
    <value name="nillable">true</value>
    <value name="form_qualified">false</value>
    <value name="is_global">false</value>
    <array name="rec_fields" type="record" depth="1">
    </array>
    <value name="modifiable">true</value>
  </record>
</Values>
</MAPSOURCE>

  <!-- nodes -->

<MAPDELETE NAME="Dropper" FIELD="/value;1;0">
</MAPDELETE>

<MAPDELETE NAME="Dropper" FIELD="/fileName;1;0">
</MAPDELETE>

<MAPDELETE NAME="Dropper" FIELD="/pattern;1;0">
</MAPDELETE>
</MAP>
</INVOKE>

<INVOKE TIMEOUT="" SERVICE="pub.flow:restorePipelineFromFile" VALIDATE-IN="$none" VALIDATE-OUT="$none">
  <COMMENT></COMMENT>

  <!-- nodes -->

<MAP MODE="INPUT">
  <MAPTARGET>

<Values version="2.0">
  <record name="xml" javaclass="com.wm.util.Values">
    <value name="node_type">record</value>
    <value name="is_public">false</value>
    <value name="field_name">restorePipelineFromFileInput</value>
    <value name="field_type">record</value>
    <value name="field_dim">0</value>
    <value name="wrapper_type">IData</value>
    <value name="nillable">true</value>
    <value name="form_qualified">false</value>
    <value name="is_global">false</value>
    <array name="rec_fields" type="record" depth="1">
      <record javaclass="com.wm.util.Values">
        <value name="node_type">unknown</value>
        <value name="is_public">false</value>
        <value name="field_name">fileName</value>
        <value name="field_type">string</value>
        <value name="field_dim">0</value>
        <value name="nillable">true</value>
        <value name="form_qualified">false</value>
        <value name="is_global">false</value>
      </record>
      <record javaclass="com.wm.util.Values">
        <value name="node_type">unknown</value>
        <value name="is_public">false</value>
        <value name="field_name">merge</value>
        <value name="field_type">string</value>
        <value name="field_dim">0</value>
        <value name="field_opt">true</value>
        <array name="field_options" type="value" depth="1">
          <value>true</value>
          <value>false</value>
        </array>
        <value name="nillable">true</value>
        <value name="form_qualified">false</value>
        <value name="is_global">false</value>
      </record>
    </array>
    <value name="modifiable">true</value>
  </record>
</Values>
</MAPTARGET>
  <MAPSOURCE>

<Values version="2.0">
  <record name="xml" javaclass="com.wm.util.Values">
    <value name="node_type">record</value>
    <value name="is_public">false</value>
    <value name="field_type">record</value>
    <value name="field_dim">0</value>
    <value name="wrapper_type">IData</value>
    <value name="nillable">true</value>
    <value name="form_qualified">false</value>
    <value name="is_global">false</value>
    <array name="rec_fields" type="record" depth="1">
    </array>
    <value name="modifiable">true</value>
  </record>
</Values>
</MAPSOURCE>

  <!-- nodes -->

<MAPSET NAME="Setter" OVERWRITE="true" VARIABLES="false" GLOBALVARIABLES="false" FIELD="/fileName;1;0">
  <DATA ENCODING="XMLValues" I18N="true">

<Values version="2.0">
  <value name="xml">GlanbiaInvoice1</value>
  <record name="type" javaclass="com.wm.util.Values">
    <value name="node_type">unknown</value>
    <value name="is_public">false</value>
    <value name="field_name">fileName</value>
    <value name="field_type">string</value>
    <value name="field_dim">0</value>
    <value name="nillable">true</value>
    <value name="form_qualified">false</value>
    <value name="is_global">false</value>
  </record>
</Values>
</DATA>
</MAPSET>
</MAP>
</INVOKE>

<INVOKE TIMEOUT="" SERVICE="cXML.invoice:mapHeader" VALIDATE-IN="$none" VALIDATE-OUT="$none">
  <COMMENT>Map cXML header from Original PO </COMMENT>

  <!-- nodes -->

<MAP MODE="INPUT">
</MAP>

<MAP MODE="OUTPUT">
  <MAPTARGET>

<Values version="2.0">
  <record name="xml" javaclass="com.wm.util.Values">
    <value name="node_type">record</value>
    <value name="is_public">false</value>
    <value name="field_type">record</value>
    <value name="field_dim">0</value>
    <value name="wrapper_type">IData</value>
    <value name="nillable">true</value>
    <value name="form_qualified">false</value>
    <value name="is_global">false</value>
    <array name="rec_fields" type="record" depth="1">
      <record javaclass="com.wm.util.Values">
        <value name="node_type">record</value>
        <value name="node_comment"></value>
        <record name="node_hints" javaclass="com.wm.util.Values">
          <value name="field_largerEditor">false</value>
          <value name="field_password">false</value>
        </record>
        <value name="is_public">false</value>
        <value name="field_name">INVOIC02</value>
        <value name="field_type">recref</value>
        <value name="field_dim">0</value>
        <value name="nillable">true</value>
        <value name="form_qualified">false</value>
        <value name="is_global">false</value>
        <value name="modifiable">true</value>
        <value name="rec_ref">PKIWmAriba.documents.IDoc:INVOIC02</value>
      </record>
      <record javaclass="com.wm.util.Values">
        <value name="node_type">record</value>
        <value name="node_comment"></value>
        <record name="node_hints" javaclass="com.wm.util.Values">
          <value name="field_largerEditor">false</value>
          <value name="field_password">false</value>
        </record>
        <value name="is_public">false</value>
        <value name="field_name">orderRequest</value>
        <value name="field_type">recref</value>
        <value name="field_dim">0</value>
        <value name="wrapper_type">IData</value>
        <value name="nillable">true</value>
        <value name="form_qualified">false</value>
        <value name="is_global">false</value>
        <value name="modifiable">true</value>
        <value name="rec_ref">PKIWmAriba.documents.doc_cXML:cXML</value>
      </record>
      <record javaclass="com.wm.util.Values">
        <value name="node_type">record</value>
        <value name="node_comment"></value>
        <record name="node_hints" javaclass="com.wm.util.Values">
          <value name="field_largerEditor">false</value>
          <value name="field_password">false</value>
        </record>
        <value name="is_public">false</value>
        <value name="field_name">Header</value>
        <value name="field_type">recref</value>
        <value name="field_dim">0</value>
        <value name="nillable">true</value>
        <value name="form_qualified">false</value>
        <value name="is_global">false</value>
        <value name="rec_closed">true</value>
        <value name="modifiable">true</value>
        <value name="rec_ref">cXML.documentType.cXML.v1_2_039.invoice:docType_Header</value>
      </record>
      <record javaclass="com.wm.util.Values">
        <value name="node_type">record</value>
        <value name="is_public">false</value>
        <value name="field_name">InvoiceRequest</value>
        <value name="field_type">recref</value>
        <value name="field_dim">0</value>
        <value name="nillable">true</value>
        <value name="form_qualified">false</value>
        <value name="is_global">false</value>
        <value name="modifiable">true</value>
        <value name="rec_ref">cXML.documentType.cXML.v1_2_039.invoice.doc_cXML_Invoice:doc_cXML_Invoice</value>
      </record>
      <record javaclass="com.wm.util.Values">
        <value name="node_type">unknown</value>
        <value name="node_comment"></value>
        <record name="node_hints" javaclass="com.wm.util.Values">
          <value name="field_usereditable">true</value>
          <value name="field_largerEditor">false</value>
          <value name="field_password">false</value>
        </record>
        <value name="is_public">false</value>
        <value name="field_name">Currency</value>
        <value name="field_type">string</value>
        <value name="field_dim">0</value>
        <array name="field_options" type="value" depth="1">
        </array>
        <value name="nillable">true</value>
        <value name="form_qualified">false</value>
        <value name="is_global">false</value>
      </record>
    </array>
    <value name="modifiable">true</value>
  </record>
</Values>
</MAPTARGET>
  <MAPSOURCE>

<Values version="2.0">
  <record name="xml" javaclass="com.wm.util.Values">
    <value name="node_type">record</value>
    <value name="is_public">false</value>
    <value name="field_type">record</value>
    <value name="field_dim">0</value>
    <value name="wrapper_type">IData</value>
    <value name="nillable">true</value>
    <value name="form_qualified">false</value>
    <value name="is_global">false</value>
    <array name="rec_fields" type="record" depth="1">
      <record javaclass="com.wm.util.Values">
        <value name="node_type">record</value>
        <value name="node_comment"></value>
        <record name="node_hints" javaclass="com.wm.util.Values">
          <value name="field_largerEditor">false</value>
          <value name="field_password">false</value>
        </record>
        <value name="is_public">false</value>
        <value name="field_name">Header</value>
        <value name="field_type">recref</value>
        <value name="field_dim">0</value>
        <value name="nillable">true</value>
        <value name="form_qualified">false</value>
        <value name="is_global">false</value>
        <value name="rec_closed">true</value>
        <value name="modifiable">true</value>
        <value name="rec_ref">cXML.documentType.cXML.v1_2_039.invoice:docType_Header</value>
      </record>
    </array>
    <value name="modifiable">true</value>
  </record>
</Values>
</MAPSOURCE>

  <!-- nodes -->

<MAPCOPY FROM="/Header;4;0;cXML.documentType.cXML.v1_2_039.invoice:docType_Header" TO="/InvoiceRequest;4;0;cXML.documentType.cXML.v1_2_039.invoice.doc_cXML_Invoice:doc_cXML_Invoice/cXML;2;0/Header;2;0">
</MAPCOPY>

<MAPDELETE FIELD="/Header;4;0;cXML.documentType.cXML.v1_2_039.invoice:docType_Header">
</MAPDELETE>

<MAPSET NAME="Setter" OVERWRITE="true" VARIABLES="false" GLOBALVARIABLES="false" FIELD="/InvoiceRequest;4;0;cXML.documentType.cXML.v1_2_039.invoice.doc_cXML_Invoice:doc_cXML_Invoice/cXML;2;0/Request;2;0/@Id;1;0">
  <DATA ENCODING="XMLValues" I18N="true">

<Values version="2.0">
  <value name="xml">cXMLData</value>
  <record name="type" javaclass="com.wm.util.Values">
    <value name="node_type">unknown</value>
    <value name="node_comment"></value>
    <record name="node_hints" javaclass="com.wm.util.Values">
      <value name="field_usereditable">true</value>
      <value name="field_largerEditor">false</value>
      <value name="field_password">false</value>
    </record>
    <value name="is_public">false</value>
    <value name="field_name">@Id</value>
    <value name="field_type">string</value>
    <value name="field_dim">0</value>
    <value name="field_opt">true</value>
    <array name="field_options" type="value" depth="1">
    </array>
    <record name="field_content_type" javaclass="com.wm.util.Values">
      <value name="contentType">1</value>
      <value name="internalType">reference</value>
      <value name="dataTypeVersion">dtVersion2</value>
      <array name="targetNames" type="record" depth="1">
        <record javaclass="com.wm.util.Values">
          <value name="xmlns">http://www.w3.org/2001/XMLSchema</value>
          <value name="ncName">string</value>
        </record>
      </array>
    </record>
    <value name="nillable">true</value>
    <value name="form_qualified">false</value>
    <value name="is_global">false</value>
  </record>
</Values>
</DATA>
</MAPSET>

<MAPSET NAME="Setter" OVERWRITE="true" VARIABLES="false" GLOBALVARIABLES="false" FIELD="/InvoiceRequest;4;0;cXML.documentType.cXML.v1_2_039.invoice.doc_cXML_Invoice:doc_cXML_Invoice/cXML;2;0/Request;2;0/@deploymentMode;1;0">
  <DATA ENCODING="XMLValues" I18N="true">

<Values version="2.0">
  <value name="xml">test</value>
  <record name="type" javaclass="com.wm.util.Values">
    <value name="node_type">unknown</value>
    <value name="node_comment"></value>
    <record name="node_hints" javaclass="com.wm.util.Values">
      <value name="field_usereditable">true</value>
      <value name="field_largerEditor">false</value>
      <value name="field_password">false</value>
    </record>
    <value name="is_public">false</value>
    <value name="field_name">@deploymentMode</value>
    <value name="field_type">string</value>
    <value name="field_dim">0</value>
    <value name="field_opt">true</value>
    <array name="field_options" type="value" depth="1">
    </array>
    <record name="field_content_type" javaclass="com.wm.util.Values">
      <array name="enumeration" type="record" depth="1">
        <record javaclass="com.wm.util.Values">
          <value name="primitiveType">0</value>
          <value name="lexRep">production</value>
          <value name="isList">false</value>
        </record>
        <record javaclass="com.wm.util.Values">
          <value name="primitiveType">0</value>
          <value name="lexRep">test</value>
          <value name="isList">false</value>
        </record>
      </array>
      <value name="contentType">1</value>
      <value name="internalType">instance</value>
      <value name="ct_class">com.wm.lang.schema.datatypev2.WmString</value>
      <value name="dataTypeVersion">dtVersion2</value>
    </record>
    <value name="nillable">true</value>
    <value name="form_qualified">false</value>
    <value name="is_global">false</value>
  </record>
</Values>
</DATA>
</MAPSET>

<MAPSET NAME="Setter" OVERWRITE="true" VARIABLES="false" GLOBALVARIABLES="false" FIELD="/Currency;1;0">
  <DATA ENCODING="XMLValues" I18N="true">

<Values version="2.0">
  <value name="xml"></value>
  <record name="type" javaclass="com.wm.util.Values">
    <value name="node_type">unknown</value>
    <value name="node_comment"></value>
    <record name="node_hints" javaclass="com.wm.util.Values">
      <value name="field_usereditable">true</value>
      <value name="field_largerEditor">false</value>
      <value name="field_password">false</value>
    </record>
    <value name="is_public">false</value>
    <value name="field_name">Currency</value>
    <value name="field_type">string</value>
    <value name="field_dim">0</value>
    <array name="field_options" type="value" depth="1">
    </array>
    <value name="nillable">true</value>
    <value name="form_qualified">false</value>
    <value name="is_global">false</value>
  </record>
</Values>
</DATA>
</MAPSET>
</MAP>
</INVOKE>

<INVOKE TIMEOUT="" SERVICE="cXML.invoice:mapInvoiceDetailRequestHeader" VALIDATE-IN="$none" VALIDATE-OUT="$none">
  <COMMENT> Invoice Request Header , Extrinsic &amp; Payment Terms</COMMENT>

  <!-- nodes -->

<MAP MODE="INPUT">
</MAP>

<MAP MODE="OUTPUT">
  <MAPTARGET>

<Values version="2.0">
  <record name="xml" javaclass="com.wm.util.Values">
    <value name="node_type">record</value>
    <value name="is_public">false</value>
    <value name="field_type">record</value>
    <value name="field_dim">0</value>
    <value name="wrapper_type">IData</value>
    <value name="nillable">true</value>
    <value name="form_qualified">false</value>
    <value name="is_global">false</value>
    <array name="rec_fields" type="record" depth="1">
      <record javaclass="com.wm.util.Values">
        <value name="node_type">record</value>
        <value name="node_comment"></value>
        <record name="node_hints" javaclass="com.wm.util.Values">
          <value name="field_largerEditor">false</value>
          <value name="field_password">false</value>
        </record>
        <value name="is_public">false</value>
        <value name="field_name">INVOIC02</value>
        <value name="field_type">recref</value>
        <value name="field_dim">0</value>
        <value name="nillable">true</value>
        <value name="form_qualified">false</value>
        <value name="is_global">false</value>
        <value name="modifiable">true</value>
        <value name="rec_ref">PKIWmAriba.documents.IDoc:INVOIC02</value>
      </record>
      <record javaclass="com.wm.util.Values">
        <value name="node_type">record</value>
        <value name="node_comment"></value>
        <record name="node_hints" javaclass="com.wm.util.Values">
          <value name="field_largerEditor">false</value>
          <value name="field_password">false</value>
        </record>
        <value name="is_public">false</value>
        <value name="field_name">orderRequest</value>
        <value name="field_type">recref</value>
        <value name="field_dim">0</value>
        <value name="wrapper_type">IData</value>
        <value name="nillable">true</value>
        <value name="form_qualified">false</value>
        <value name="is_global">false</value>
        <value name="modifiable">true</value>
        <value name="rec_ref">PKIWmAriba.documents.doc_cXML:cXML</value>
      </record>
      <record javaclass="com.wm.util.Values">
        <value name="node_type">record</value>
        <value name="is_public">false</value>
        <value name="field_name">InvoiceRequest</value>
        <value name="field_type">recref</value>
        <value name="field_dim">0</value>
        <value name="nillable">true</value>
        <value name="form_qualified">false</value>
        <value name="is_global">false</value>
        <value name="modifiable">true</value>
        <value name="rec_ref">cXML.documentType.cXML.v1_2_039.invoice.doc_cXML_Invoice:doc_cXML_Invoice</value>
      </record>
      <record javaclass="com.wm.util.Values">
        <value name="node_type">unknown</value>
        <value name="is_public">false</value>
        <value name="field_name">Currency</value>
        <value name="field_type">string</value>
        <value name="field_dim">0</value>
        <value name="nillable">true</value>
        <value name="form_qualified">false</value>
        <value name="is_global">false</value>
      </record>
      <record javaclass="com.wm.util.Values">
        <value name="node_type">record</value>
        <value name="node_comment"></value>
        <record name="node_hints" javaclass="com.wm.util.Values">
          <value name="field_largerEditor">false</value>
          <value name="field_password">false</value>
        </record>
        <value name="is_public">false</value>
        <value name="field_name">InvoiceDetailRequestHeader</value>
        <value name="field_type">recref</value>
        <value name="field_dim">0</value>
        <value name="nillable">true</value>
        <value name="form_qualified">false</value>
        <value name="is_global">false</value>
        <value name="rec_closed">true</value>
        <value name="modifiable">true</value>
        <value name="rec_ref">cXML.documentType.cXML.v1_2_039.invoice:docType_InvoiceDetailRequestHeader</value>
      </record>
    </array>
    <value name="modifiable">true</value>
  </record>
</Values>
</MAPTARGET>
  <MAPSOURCE>

<Values version="2.0">
  <record name="xml" javaclass="com.wm.util.Values">
    <value name="node_type">record</value>
    <value name="is_public">false</value>
    <value name="field_type">record</value>
    <value name="field_dim">0</value>
    <value name="wrapper_type">IData</value>
    <value name="nillable">true</value>
    <value name="form_qualified">false</value>
    <value name="is_global">false</value>
    <array name="rec_fields" type="record" depth="1">
      <record javaclass="com.wm.util.Values">
        <value name="node_type">record</value>
        <value name="node_comment"></value>
        <record name="node_hints" javaclass="com.wm.util.Values">
          <value name="field_largerEditor">false</value>
          <value name="field_password">false</value>
        </record>
        <value name="is_public">false</value>
        <value name="field_name">InvoiceDetailRequestHeader</value>
        <value name="field_type">recref</value>
        <value name="field_dim">0</value>
        <value name="nillable">true</value>
        <value name="form_qualified">false</value>
        <value name="is_global">false</value>
        <value name="rec_closed">true</value>
        <value name="modifiable">true</value>
        <value name="rec_ref">cXML.documentType.cXML.v1_2_039.invoice:docType_InvoiceDetailRequestHeader</value>
      </record>
    </array>
    <value name="modifiable">true</value>
  </record>
</Values>
</MAPSOURCE>

  <!-- nodes -->

<MAPCOPY FROM="/InvoiceDetailRequestHeader;4;0;cXML.documentType.cXML.v1_2_039.invoice:docType_InvoiceDetailRequestHeader" TO="/InvoiceRequest;4;0;cXML.documentType.cXML.v1_2_039.invoice.doc_cXML_Invoice:doc_cXML_Invoice/cXML;2;0/Request;2;0/InvoiceDetailRequest;2;0/InvoiceDetailRequestHeader;2;0">
</MAPCOPY>

<MAPDELETE FIELD="/InvoiceDetailRequestHeader;4;0;cXML.documentType.cXML.v1_2_039.invoice:docType_InvoiceDetailRequestHeader">
</MAPDELETE>
</MAP>
</INVOKE>

<INVOKE TIMEOUT="" SERVICE="cXML.invoice:mapInvoiceDetailOrder" VALIDATE-IN="$none" VALIDATE-OUT="$none">
  <COMMENT>Order and Supplier Reference Mapping</COMMENT>

  <!-- nodes -->

<MAP MODE="INPUT">
</MAP>

<MAP MODE="OUTPUT">
  <MAPTARGET>

<Values version="2.0">
  <record name="xml" javaclass="com.wm.util.Values">
    <value name="node_type">record</value>
    <value name="is_public">false</value>
    <value name="field_type">record</value>
    <value name="field_dim">0</value>
    <value name="wrapper_type">IData</value>
    <value name="nillable">true</value>
    <value name="form_qualified">false</value>
    <value name="is_global">false</value>
    <array name="rec_fields" type="record" depth="1">
      <record javaclass="com.wm.util.Values">
        <value name="node_type">record</value>
        <value name="node_comment"></value>
        <record name="node_hints" javaclass="com.wm.util.Values">
          <value name="field_largerEditor">false</value>
          <value name="field_password">false</value>
        </record>
        <value name="is_public">false</value>
        <value name="field_name">INVOIC02</value>
        <value name="field_type">recref</value>
        <value name="field_dim">0</value>
        <value name="nillable">true</value>
        <value name="form_qualified">false</value>
        <value name="is_global">false</value>
        <value name="modifiable">true</value>
        <value name="rec_ref">PKIWmAriba.documents.IDoc:INVOIC02</value>
      </record>
      <record javaclass="com.wm.util.Values">
        <value name="node_type">record</value>
        <value name="node_comment"></value>
        <record name="node_hints" javaclass="com.wm.util.Values">
          <value name="field_largerEditor">false</value>
          <value name="field_password">false</value>
        </record>
        <value name="is_public">false</value>
        <value name="field_name">orderRequest</value>
        <value name="field_type">recref</value>
        <value name="field_dim">0</value>
        <value name="wrapper_type">IData</value>
        <value name="nillable">true</value>
        <value name="form_qualified">false</value>
        <value name="is_global">false</value>
        <value name="modifiable">true</value>
        <value name="rec_ref">PKIWmAriba.documents.doc_cXML:cXML</value>
      </record>
      <record javaclass="com.wm.util.Values">
        <value name="node_type">record</value>
        <value name="is_public">false</value>
        <value name="field_name">InvoiceRequest</value>
        <value name="field_type">recref</value>
        <value name="field_dim">0</value>
        <value name="nillable">true</value>
        <value name="form_qualified">false</value>
        <value name="is_global">false</value>
        <value name="modifiable">true</value>
        <value name="rec_ref">cXML.documentType.cXML.v1_2_039.invoice.doc_cXML_Invoice:doc_cXML_Invoice</value>
      </record>
      <record javaclass="com.wm.util.Values">
        <value name="node_type">unknown</value>
        <value name="is_public">false</value>
        <value name="field_name">Currency</value>
        <value name="field_type">string</value>
        <value name="field_dim">0</value>
        <value name="nillable">true</value>
        <value name="form_qualified">false</value>
        <value name="is_global">false</value>
      </record>
      <record javaclass="com.wm.util.Values">
        <value name="node_type">record</value>
        <value name="node_comment"></value>
        <record name="node_hints" javaclass="com.wm.util.Values">
          <value name="field_largerEditor">false</value>
          <value name="field_password">false</value>
        </record>
        <value name="is_public">false</value>
        <value name="field_name">InvoiceDetailOrderInfo</value>
        <value name="field_type">recref</value>
        <value name="field_dim">0</value>
        <value name="nillable">true</value>
        <value name="form_qualified">false</value>
        <value name="is_global">false</value>
        <value name="rec_closed">true</value>
        <value name="modifiable">true</value>
        <value name="rec_ref">cXML.documentType.cXML.v1_2_039.invoice.doc_cXML_Invoice:docType_InvoiceDetailOrderInfo</value>
      </record>
    </array>
    <value name="modifiable">true</value>
  </record>
</Values>
</MAPTARGET>
  <MAPSOURCE>

<Values version="2.0">
  <record name="xml" javaclass="com.wm.util.Values">
    <value name="node_type">record</value>
    <value name="is_public">false</value>
    <value name="field_type">record</value>
    <value name="field_dim">0</value>
    <value name="wrapper_type">IData</value>
    <value name="nillable">true</value>
    <value name="form_qualified">false</value>
    <value name="is_global">false</value>
    <array name="rec_fields" type="record" depth="1">
      <record javaclass="com.wm.util.Values">
        <value name="node_type">record</value>
        <value name="node_comment"></value>
        <record name="node_hints" javaclass="com.wm.util.Values">
          <value name="field_largerEditor">false</value>
          <value name="field_password">false</value>
        </record>
        <value name="is_public">false</value>
        <value name="field_name">InvoiceDetailOrderInfo</value>
        <value name="field_type">recref</value>
        <value name="field_dim">0</value>
        <value name="nillable">true</value>
        <value name="form_qualified">false</value>
        <value name="is_global">false</value>
        <value name="rec_closed">true</value>
        <value name="modifiable">true</value>
        <value name="rec_ref">cXML.documentType.cXML.v1_2_039.invoice.doc_cXML_Invoice:docType_InvoiceDetailOrderInfo</value>
      </record>
    </array>
    <value name="modifiable">true</value>
  </record>
</Values>
</MAPSOURCE>

  <!-- nodes -->

<MAPCOPY FROM="/InvoiceDetailOrderInfo;4;0;cXML.documentType.cXML.v1_2_039.invoice.doc_cXML_Invoice:docType_InvoiceDetailOrderInfo" TO="/InvoiceRequest;4;0;cXML.documentType.cXML.v1_2_039.invoice.doc_cXML_Invoice:doc_cXML_Invoice/cXML;2;0/Request;2;0/InvoiceDetailRequest;2;0/InvoiceDetailOrder;2;1/InvoiceDetailOrderInfo;4;0;cXML.documentType.cXML.v1_2_039.invoice.doc_cXML_Invoice:docType_InvoiceDetailOrderInfo">
</MAPCOPY>

<MAPDELETE FIELD="/InvoiceDetailOrderInfo;4;0;cXML.documentType.cXML.v1_2_039.invoice.doc_cXML_Invoice:docType_InvoiceDetailOrderInfo">
</MAPDELETE>
</MAP>
</INVOKE>

<BRANCH TIMEOUT="" SWITCH="/INVOIC02/INVOIC02/IDOC/E1EDK01/BSART">
  <COMMENT>check for CreditMemo </COMMENT>

  <!-- nodes -->

<MAP NAME="CRME" TIMEOUT="" MODE="STANDALONE">
  <COMMENT>Mapping Invoice purpose and operation</COMMENT>
  <MAPTARGET>

<Values version="2.0">
  <record name="xml" javaclass="com.wm.util.Values">
    <value name="node_type">record</value>
    <value name="is_public">false</value>
    <value name="field_type">record</value>
    <value name="field_dim">0</value>
    <value name="wrapper_type">IData</value>
    <value name="nillable">true</value>
    <value name="form_qualified">false</value>
    <value name="is_global">false</value>
    <array name="rec_fields" type="record" depth="1">
      <record javaclass="com.wm.util.Values">
        <value name="node_type">record</value>
        <value name="node_comment"></value>
        <record name="node_hints" javaclass="com.wm.util.Values">
          <value name="field_largerEditor">false</value>
          <value name="field_password">false</value>
        </record>
        <value name="is_public">false</value>
        <value name="field_name">INVOIC02</value>
        <value name="field_type">recref</value>
        <value name="field_dim">0</value>
        <value name="nillable">true</value>
        <value name="form_qualified">false</value>
        <value name="is_global">false</value>
        <value name="modifiable">true</value>
        <value name="rec_ref">PKIWmAriba.documents.IDoc:INVOIC02</value>
      </record>
      <record javaclass="com.wm.util.Values">
        <value name="node_type">record</value>
        <value name="node_comment"></value>
        <record name="node_hints" javaclass="com.wm.util.Values">
          <value name="field_largerEditor">false</value>
          <value name="field_password">false</value>
        </record>
        <value name="is_public">false</value>
        <value name="field_name">orderRequest</value>
        <value name="field_type">recref</value>
        <value name="field_dim">0</value>
        <value name="wrapper_type">IData</value>
        <value name="nillable">true</value>
        <value name="form_qualified">false</value>
        <value name="is_global">false</value>
        <value name="modifiable">true</value>
        <value name="rec_ref">PKIWmAriba.documents.doc_cXML:cXML</value>
      </record>
      <record javaclass="com.wm.util.Values">
        <value name="node_type">record</value>
        <value name="is_public">false</value>
        <value name="field_name">InvoiceRequest</value>
        <value name="field_type">recref</value>
        <value name="field_dim">0</value>
        <value name="nillable">true</value>
        <value name="form_qualified">false</value>
        <value name="is_global">false</value>
        <value name="modifiable">true</value>
        <value name="rec_ref">cXML.documentType.cXML.v1_2_039.invoice.doc_cXML_Invoice:doc_cXML_Invoice</value>
      </record>
      <record javaclass="com.wm.util.Values">
        <value name="node_type">unknown</value>
        <value name="is_public">false</value>
        <value name="field_name">invoiceDate</value>
        <value name="field_type">string</value>
        <value name="field_dim">0</value>
        <value name="nillable">true</value>
        <value name="form_qualified">false</value>
        <value name="is_global">false</value>
      </record>
      <record javaclass="com.wm.util.Values">
        <value name="node_type">unknown</value>
        <value name="is_public">false</value>
        <value name="field_name">CRMemo</value>
        <value name="field_type">string</value>
        <value name="field_dim">0</value>
        <value name="nillable">true</value>
        <value name="form_qualified">false</value>
        <value name="is_global">false</value>
      </record>
    </array>
    <value name="modifiable">true</value>
  </record>
</Values>
</MAPTARGET>
  <MAPSOURCE>

<Values version="2.0">
  <record name="xml" javaclass="com.wm.util.Values">
    <value name="node_type">record</value>
    <value name="is_public">false</value>
    <value name="field_type">record</value>
    <value name="field_dim">0</value>
    <value name="wrapper_type">IData</value>
    <value name="nillable">true</value>
    <value name="form_qualified">false</value>
    <value name="is_global">false</value>
    <array name="rec_fields" type="record" depth="1">
    </array>
    <value name="modifiable">true</value>
  </record>
</Values>
</MAPSOURCE>

  <!-- nodes -->

<MAPSET NAME="Setter" OVERWRITE="true" VARIABLES="false" GLOBALVARIABLES="false" FIELD="/CRMemo;1;0">
  <DATA ENCODING="XMLValues" I18N="true">

<Values version="2.0">
  <value name="xml">Yes</value>
  <record name="type" javaclass="com.wm.util.Values">
    <value name="node_type">record</value>
    <value name="is_public">false</value>
    <value name="field_name">CRMemo</value>
    <value name="field_type">string</value>
    <value name="field_dim">0</value>
    <value name="nillable">true</value>
    <value name="form_qualified">false</value>
    <value name="is_global">false</value>
  </record>
</Values>
</DATA>
</MAPSET>
</MAP>

<MAP NAME="$default" TIMEOUT="" MODE="STANDALONE">
  <COMMENT>Mapping Invoice purpose and operation</COMMENT>
  <MAPTARGET>

<Values version="2.0">
  <record name="xml" javaclass="com.wm.util.Values">
    <value name="node_type">record</value>
    <value name="is_public">false</value>
    <value name="field_type">record</value>
    <value name="field_dim">0</value>
    <value name="wrapper_type">IData</value>
    <value name="nillable">true</value>
    <value name="form_qualified">false</value>
    <value name="is_global">false</value>
    <array name="rec_fields" type="record" depth="1">
      <record javaclass="com.wm.util.Values">
        <value name="node_type">record</value>
        <value name="node_comment"></value>
        <record name="node_hints" javaclass="com.wm.util.Values">
          <value name="field_largerEditor">false</value>
          <value name="field_password">false</value>
        </record>
        <value name="is_public">false</value>
        <value name="field_name">INVOIC02</value>
        <value name="field_type">recref</value>
        <value name="field_dim">0</value>
        <value name="nillable">true</value>
        <value name="form_qualified">false</value>
        <value name="is_global">false</value>
        <value name="modifiable">true</value>
        <value name="rec_ref">PKIWmAriba.documents.IDoc:INVOIC02</value>
      </record>
      <record javaclass="com.wm.util.Values">
        <value name="node_type">record</value>
        <value name="node_comment"></value>
        <record name="node_hints" javaclass="com.wm.util.Values">
          <value name="field_largerEditor">false</value>
          <value name="field_password">false</value>
        </record>
        <value name="is_public">false</value>
        <value name="field_name">orderRequest</value>
        <value name="field_type">recref</value>
        <value name="field_dim">0</value>
        <value name="wrapper_type">IData</value>
        <value name="nillable">true</value>
        <value name="form_qualified">false</value>
        <value name="is_global">false</value>
        <value name="modifiable">true</value>
        <value name="rec_ref">PKIWmAriba.documents.doc_cXML:cXML</value>
      </record>
      <record javaclass="com.wm.util.Values">
        <value name="node_type">record</value>
        <value name="is_public">false</value>
        <value name="field_name">InvoiceRequest</value>
        <value name="field_type">recref</value>
        <value name="field_dim">0</value>
        <value name="nillable">true</value>
        <value name="form_qualified">false</value>
        <value name="is_global">false</value>
        <value name="modifiable">true</value>
        <value name="rec_ref">cXML.documentType.cXML.v1_2_039.invoice.doc_cXML_Invoice:doc_cXML_Invoice</value>
      </record>
      <record javaclass="com.wm.util.Values">
        <value name="node_type">unknown</value>
        <value name="is_public">false</value>
        <value name="field_name">invoiceDate</value>
        <value name="field_type">string</value>
        <value name="field_dim">0</value>
        <value name="nillable">true</value>
        <value name="form_qualified">false</value>
        <value name="is_global">false</value>
      </record>
      <record javaclass="com.wm.util.Values">
        <value name="node_type">unknown</value>
        <value name="is_public">false</value>
        <value name="field_name">CRMemo</value>
        <value name="field_type">string</value>
        <value name="field_dim">0</value>
        <value name="nillable">true</value>
        <value name="form_qualified">false</value>
        <value name="is_global">false</value>
      </record>
    </array>
    <value name="modifiable">true</value>
  </record>
</Values>
</MAPTARGET>
  <MAPSOURCE>

<Values version="2.0">
  <record name="xml" javaclass="com.wm.util.Values">
    <value name="node_type">record</value>
    <value name="is_public">false</value>
    <value name="field_type">record</value>
    <value name="field_dim">0</value>
    <value name="wrapper_type">IData</value>
    <value name="nillable">true</value>
    <value name="form_qualified">false</value>
    <value name="is_global">false</value>
    <array name="rec_fields" type="record" depth="1">
    </array>
    <value name="modifiable">true</value>
  </record>
</Values>
</MAPSOURCE>

  <!-- nodes -->

<MAPSET NAME="Setter" OVERWRITE="true" VARIABLES="false" GLOBALVARIABLES="false" FIELD="/CRMemo;1;0">
  <DATA ENCODING="XMLValues" I18N="true">

<Values version="2.0">
  <value name="xml">No</value>
  <record name="type" javaclass="com.wm.util.Values">
    <value name="node_type">record</value>
    <value name="is_public">false</value>
    <value name="field_name">CRMemo</value>
    <value name="field_type">string</value>
    <value name="field_dim">0</value>
    <value name="nillable">true</value>
    <value name="form_qualified">false</value>
    <value name="is_global">false</value>
  </record>
</Values>
</DATA>
</MAPSET>
</MAP>
</BRANCH>

<BRANCH TIMEOUT="" SWITCH="/INVOIC02/INVOIC02/IDOC[0]/E1EDK01/CURCY">
  <COMMENT>map Currency</COMMENT>

  <!-- nodes -->

<MAP NAME="$default" TIMEOUT="" MODE="STANDALONE">
  <COMMENT>Currency from Invoice IDOC</COMMENT>
  <MAPTARGET>

<Values version="2.0">
  <record name="xml" javaclass="com.wm.util.Values">
    <value name="node_type">record</value>
    <value name="is_public">false</value>
    <value name="field_type">record</value>
    <value name="field_dim">0</value>
    <value name="wrapper_type">IData</value>
    <value name="nillable">true</value>
    <value name="form_qualified">false</value>
    <value name="is_global">false</value>
    <array name="rec_fields" type="record" depth="1">
      <record javaclass="com.wm.util.Values">
        <value name="node_type">record</value>
        <value name="node_comment"></value>
        <record name="node_hints" javaclass="com.wm.util.Values">
          <value name="field_largerEditor">false</value>
          <value name="field_password">false</value>
        </record>
        <value name="is_public">false</value>
        <value name="field_name">INVOIC02</value>
        <value name="field_type">recref</value>
        <value name="field_dim">0</value>
        <value name="nillable">true</value>
        <value name="form_qualified">false</value>
        <value name="is_global">false</value>
        <value name="modifiable">true</value>
        <value name="rec_ref">PKIWmAriba.documents.IDoc:INVOIC02</value>
      </record>
      <record javaclass="com.wm.util.Values">
        <value name="node_type">record</value>
        <value name="node_comment"></value>
        <record name="node_hints" javaclass="com.wm.util.Values">
          <value name="field_largerEditor">false</value>
          <value name="field_password">false</value>
        </record>
        <value name="is_public">false</value>
        <value name="field_name">orderRequest</value>
        <value name="field_type">recref</value>
        <value name="field_dim">0</value>
        <value name="wrapper_type">IData</value>
        <value name="nillable">true</value>
        <value name="form_qualified">false</value>
        <value name="is_global">false</value>
        <value name="modifiable">true</value>
        <value name="rec_ref">PKIWmAriba.documents.doc_cXML:cXML</value>
      </record>
      <record javaclass="com.wm.util.Values">
        <value name="node_type">record</value>
        <value name="is_public">false</value>
        <value name="field_name">InvoiceRequest</value>
        <value name="field_type">recref</value>
        <value name="field_dim">0</value>
        <value name="nillable">true</value>
        <value name="form_qualified">false</value>
        <value name="is_global">false</value>
        <value name="modifiable">true</value>
        <value name="rec_ref">cXML.documentType.cXML.v1_2_039.invoice.doc_cXML_Invoice:doc_cXML_Invoice</value>
      </record>
      <record javaclass="com.wm.util.Values">
        <value name="node_type">unknown</value>
        <value name="is_public">false</value>
        <value name="field_name">Currency</value>
        <value name="field_type">string</value>
        <value name="field_dim">0</value>
        <value name="nillable">true</value>
        <value name="form_qualified">false</value>
        <value name="is_global">false</value>
      </record>
      <record javaclass="com.wm.util.Values">
        <value name="node_type">unknown</value>
        <value name="is_public">false</value>
        <value name="field_name">CRMemo</value>
        <value name="field_type">string</value>
        <value name="field_dim">0</value>
        <value name="nillable">true</value>
        <value name="form_qualified">false</value>
        <value name="is_global">false</value>
      </record>
    </array>
    <value name="modifiable">true</value>
  </record>
</Values>
</MAPTARGET>
  <MAPSOURCE>

<Values version="2.0">
  <record name="xml" javaclass="com.wm.util.Values">
    <value name="node_type">record</value>
    <value name="is_public">false</value>
    <value name="field_type">record</value>
    <value name="field_dim">0</value>
    <value name="wrapper_type">IData</value>
    <value name="nillable">true</value>
    <value name="form_qualified">false</value>
    <value name="is_global">false</value>
    <array name="rec_fields" type="record" depth="1">
    </array>
    <value name="modifiable">true</value>
  </record>
</Values>
</MAPSOURCE>

  <!-- nodes -->

<MAPSET NAME="Setter" OVERWRITE="true" VARIABLES="true" GLOBALVARIABLES="false" FIELD="/Currency;1;0">
  <DATA ENCODING="XMLValues" I18N="true">

<Values version="2.0">
  <value name="xml">%INVOIC02/INVOIC02/IDOC[0]/E1EDK01/CURCY%</value>
  <record name="type" javaclass="com.wm.util.Values">
    <value name="node_type">unknown</value>
    <value name="node_comment"></value>
    <record name="node_hints" javaclass="com.wm.util.Values">
      <value name="field_usereditable">true</value>
      <value name="field_largerEditor">false</value>
      <value name="field_password">false</value>
    </record>
    <value name="is_public">false</value>
    <value name="field_name">Currency</value>
    <value name="field_type">string</value>
    <value name="field_dim">0</value>
    <array name="field_options" type="value" depth="1">
    </array>
    <value name="nillable">true</value>
    <value name="form_qualified">false</value>
    <value name="is_global">false</value>
  </record>
</Values>
</DATA>
</MAPSET>
</MAP>

<MAP NAME="$null" TIMEOUT="" MODE="STANDALONE">
  <COMMENT>Map currency from PO</COMMENT>
  <MAPTARGET>

<Values version="2.0">
  <record name="xml" javaclass="com.wm.util.Values">
    <value name="node_type">record</value>
    <value name="is_public">false</value>
    <value name="field_type">record</value>
    <value name="field_dim">0</value>
    <value name="wrapper_type">IData</value>
    <value name="nillable">true</value>
    <value name="form_qualified">false</value>
    <value name="is_global">false</value>
    <array name="rec_fields" type="record" depth="1">
      <record javaclass="com.wm.util.Values">
        <value name="node_type">record</value>
        <value name="node_comment"></value>
        <record name="node_hints" javaclass="com.wm.util.Values">
          <value name="field_largerEditor">false</value>
          <value name="field_password">false</value>
        </record>
        <value name="is_public">false</value>
        <value name="field_name">INVOIC02</value>
        <value name="field_type">recref</value>
        <value name="field_dim">0</value>
        <value name="nillable">true</value>
        <value name="form_qualified">false</value>
        <value name="is_global">false</value>
        <value name="modifiable">true</value>
        <value name="rec_ref">PKIWmAriba.documents.IDoc:INVOIC02</value>
      </record>
      <record javaclass="com.wm.util.Values">
        <value name="node_type">record</value>
        <value name="node_comment"></value>
        <record name="node_hints" javaclass="com.wm.util.Values">
          <value name="field_largerEditor">false</value>
          <value name="field_password">false</value>
        </record>
        <value name="is_public">false</value>
        <value name="field_name">orderRequest</value>
        <value name="field_type">recref</value>
        <value name="field_dim">0</value>
        <value name="wrapper_type">IData</value>
        <value name="nillable">true</value>
        <value name="form_qualified">false</value>
        <value name="is_global">false</value>
        <value name="modifiable">true</value>
        <value name="rec_ref">PKIWmAriba.documents.doc_cXML:cXML</value>
      </record>
      <record javaclass="com.wm.util.Values">
        <value name="node_type">record</value>
        <value name="is_public">false</value>
        <value name="field_name">InvoiceRequest</value>
        <value name="field_type">recref</value>
        <value name="field_dim">0</value>
        <value name="nillable">true</value>
        <value name="form_qualified">false</value>
        <value name="is_global">false</value>
        <value name="modifiable">true</value>
        <value name="rec_ref">cXML.documentType.cXML.v1_2_039.invoice.doc_cXML_Invoice:doc_cXML_Invoice</value>
      </record>
      <record javaclass="com.wm.util.Values">
        <value name="node_type">unknown</value>
        <value name="is_public">false</value>
        <value name="field_name">Currency</value>
        <value name="field_type">string</value>
        <value name="field_dim">0</value>
        <value name="nillable">true</value>
        <value name="form_qualified">false</value>
        <value name="is_global">false</value>
      </record>
      <record javaclass="com.wm.util.Values">
        <value name="node_type">unknown</value>
        <value name="is_public">false</value>
        <value name="field_name">CRMemo</value>
        <value name="field_type">string</value>
        <value name="field_dim">0</value>
        <value name="nillable">true</value>
        <value name="form_qualified">false</value>
        <value name="is_global">false</value>
      </record>
    </array>
    <value name="modifiable">true</value>
  </record>
</Values>
</MAPTARGET>
  <MAPSOURCE>

<Values version="2.0">
  <record name="xml" javaclass="com.wm.util.Values">
    <value name="node_type">record</value>
    <value name="is_public">false</value>
    <value name="field_type">record</value>
    <value name="field_dim">0</value>
    <value name="wrapper_type">IData</value>
    <value name="nillable">true</value>
    <value name="form_qualified">false</value>
    <value name="is_global">false</value>
    <array name="rec_fields" type="record" depth="1">
    </array>
    <value name="modifiable">true</value>
  </record>
</Values>
</MAPSOURCE>

  <!-- nodes -->

<MAPSET NAME="Setter" OVERWRITE="true" VARIABLES="true" GLOBALVARIABLES="false" FIELD="/Currency;1;0">
  <DATA ENCODING="XMLValues" I18N="true">

<Values version="2.0">
  <value name="xml">%orderRequest/cXML/Request/OrderRequest/ItemOut[0]/ItemDetail/UnitPrice/Money/@currency%</value>
  <record name="type" javaclass="com.wm.util.Values">
    <value name="node_type">unknown</value>
    <value name="node_comment"></value>
    <record name="node_hints" javaclass="com.wm.util.Values">
      <value name="field_usereditable">true</value>
      <value name="field_largerEditor">false</value>
      <value name="field_password">false</value>
    </record>
    <value name="is_public">false</value>
    <value name="field_name">Currency</value>
    <value name="field_type">string</value>
    <value name="field_dim">0</value>
    <array name="field_options" type="value" depth="1">
    </array>
    <value name="nillable">true</value>
    <value name="form_qualified">false</value>
    <value name="is_global">false</value>
  </record>
</Values>
</DATA>
</MAPSET>
</MAP>
</BRANCH>

<INVOKE TIMEOUT="" SERVICE="cXML.invoice:mapLiteItems" VALIDATE-IN="$none" VALIDATE-OUT="$none">
  <COMMENT>Item Details mapping</COMMENT>

  <!-- nodes -->

<MAP MODE="INPUT">
  <MAPTARGET>

<Values version="2.0">
  <record name="xml" javaclass="com.wm.util.Values">
    <value name="node_type">record</value>
    <value name="is_public">false</value>
    <value name="field_type">record</value>
    <value name="field_dim">0</value>
    <value name="wrapper_type">IData</value>
    <value name="nillable">true</value>
    <value name="form_qualified">false</value>
    <value name="is_global">false</value>
    <array name="rec_fields" type="record" depth="1">
      <record javaclass="com.wm.util.Values">
        <value name="node_type">record</value>
        <value name="node_comment"></value>
        <record name="node_hints" javaclass="com.wm.util.Values">
          <value name="field_largerEditor">false</value>
          <value name="field_password">false</value>
        </record>
        <value name="is_public">false</value>
        <value name="field_name">INVOIC02</value>
        <value name="field_type">recref</value>
        <value name="field_dim">0</value>
        <value name="wrapper_type">IData</value>
        <value name="nillable">true</value>
        <value name="form_qualified">false</value>
        <value name="is_global">false</value>
        <value name="modifiable">true</value>
        <value name="rec_ref">PKIWmAriba.documents.IDoc:INVOIC02</value>
      </record>
      <record javaclass="com.wm.util.Values">
        <value name="node_type">record</value>
        <value name="node_comment"></value>
        <record name="node_hints" javaclass="com.wm.util.Values">
          <value name="field_largerEditor">false</value>
          <value name="field_password">false</value>
        </record>
        <value name="is_public">false</value>
        <value name="field_name">orderRequest</value>
        <value name="field_type">recref</value>
        <value name="field_dim">0</value>
        <value name="wrapper_type">IData</value>
        <value name="nillable">true</value>
        <value name="form_qualified">false</value>
        <value name="is_global">false</value>
        <value name="modifiable">true</value>
        <value name="rec_ref">PKIWmAriba.documents.doc_cXML:cXML</value>
      </record>
      <record javaclass="com.wm.util.Values">
        <value name="node_type">record</value>
        <value name="node_comment"></value>
        <record name="node_hints" javaclass="com.wm.util.Values">
          <value name="field_usereditable">true</value>
          <value name="field_largerEditor">false</value>
          <value name="field_password">false</value>
        </record>
        <value name="is_public">false</value>
        <value name="field_name">CRMemo</value>
        <value name="field_type">string</value>
        <value name="field_dim">0</value>
        <array name="field_options" type="value" depth="1">
        </array>
        <value name="nillable">true</value>
        <value name="form_qualified">false</value>
        <value name="is_global">false</value>
      </record>
      <record javaclass="com.wm.util.Values">
        <value name="node_type">unknown</value>
        <value name="node_comment"></value>
        <record name="node_hints" javaclass="com.wm.util.Values">
          <value name="field_usereditable">true</value>
          <value name="field_largerEditor">false</value>
          <value name="field_password">false</value>
        </record>
        <value name="is_public">false</value>
        <value name="field_name">Currency</value>
        <value name="field_type">string</value>
        <value name="field_dim">0</value>
        <array name="field_options" type="value" depth="1">
        </array>
        <value name="nillable">true</value>
        <value name="form_qualified">false</value>
        <value name="is_global">false</value>
      </record>
      <record javaclass="com.wm.util.Values">
        <value name="node_type">unknown</value>
        <value name="node_comment"></value>
        <record name="node_hints" javaclass="com.wm.util.Values">
          <value name="field_usereditable">true</value>
          <value name="field_largerEditor">false</value>
          <value name="field_password">false</value>
        </record>
        <value name="is_public">false</value>
        <value name="field_name">invoiceDate</value>
        <value name="field_type">string</value>
        <value name="field_dim">0</value>
        <array name="field_options" type="value" depth="1">
        </array>
        <record name="field_content_type" javaclass="com.wm.util.Values">
          <value name="contentType">1</value>
          <value name="internalType">reference</value>
          <value name="dataTypeVersion">dtVersion2</value>
          <array name="targetNames" type="record" depth="1">
            <record javaclass="com.wm.util.Values">
              <value name="xmlns">http://www.w3.org/2001/XMLSchema</value>
              <value name="ncName">string</value>
            </record>
          </array>
        </record>
        <value name="nillable">true</value>
        <value name="form_qualified">false</value>
        <value name="is_global">false</value>
      </record>
    </array>
    <value name="modifiable">true</value>
  </record>
</Values>
</MAPTARGET>
  <MAPSOURCE>

<Values version="2.0">
  <record name="xml" javaclass="com.wm.util.Values">
    <value name="node_type">record</value>
    <value name="is_public">false</value>
    <value name="field_type">record</value>
    <value name="field_dim">0</value>
    <value name="wrapper_type">IData</value>
    <value name="nillable">true</value>
    <value name="form_qualified">false</value>
    <value name="is_global">false</value>
    <array name="rec_fields" type="record" depth="1">
      <record javaclass="com.wm.util.Values">
        <value name="node_type">record</value>
        <value name="node_comment"></value>
        <record name="node_hints" javaclass="com.wm.util.Values">
          <value name="field_largerEditor">false</value>
          <value name="field_password">false</value>
        </record>
        <value name="is_public">false</value>
        <value name="field_name">INVOIC02</value>
        <value name="field_type">recref</value>
        <value name="field_dim">0</value>
        <value name="nillable">true</value>
        <value name="form_qualified">false</value>
        <value name="is_global">false</value>
        <value name="modifiable">true</value>
        <value name="rec_ref">PKIWmAriba.documents.IDoc:INVOIC02</value>
      </record>
      <record javaclass="com.wm.util.Values">
        <value name="node_type">record</value>
        <value name="node_comment"></value>
        <record name="node_hints" javaclass="com.wm.util.Values">
          <value name="field_largerEditor">false</value>
          <value name="field_password">false</value>
        </record>
        <value name="is_public">false</value>
        <value name="field_name">orderRequest</value>
        <value name="field_type">recref</value>
        <value name="field_dim">0</value>
        <value name="wrapper_type">IData</value>
        <value name="nillable">true</value>
        <value name="form_qualified">false</value>
        <value name="is_global">false</value>
        <value name="modifiable">true</value>
        <value name="rec_ref">PKIWmAriba.documents.doc_cXML:cXML</value>
      </record>
      <record javaclass="com.wm.util.Values">
        <value name="node_type">record</value>
        <value name="is_public">false</value>
        <value name="field_name">InvoiceRequest</value>
        <value name="field_type">recref</value>
        <value name="field_dim">0</value>
        <value name="nillable">true</value>
        <value name="form_qualified">false</value>
        <value name="is_global">false</value>
        <value name="modifiable">true</value>
        <value name="rec_ref">cXML.documentType.cXML.v1_2_039.invoice.doc_cXML_Invoice:doc_cXML_Invoice</value>
      </record>
      <record javaclass="com.wm.util.Values">
        <value name="node_type">unknown</value>
        <value name="is_public">false</value>
        <value name="field_name">Currency</value>
        <value name="field_type">string</value>
        <value name="field_dim">0</value>
        <value name="nillable">true</value>
        <value name="form_qualified">false</value>
        <value name="is_global">false</value>
      </record>
      <record javaclass="com.wm.util.Values">
        <value name="node_type">unknown</value>
        <value name="is_public">false</value>
        <value name="field_name">CRMemo</value>
        <value name="field_type">string</value>
        <value name="field_dim">0</value>
        <value name="nillable">true</value>
        <value name="form_qualified">false</value>
        <value name="is_global">false</value>
      </record>
    </array>
    <value name="modifiable">true</value>
  </record>
</Values>
</MAPSOURCE>

  <!-- nodes -->

<MAPCOPY FROM="/InvoiceRequest;4;0;cXML.documentType.cXML.v1_2_039.invoice.doc_cXML_Invoice:doc_cXML_Invoice/cXML;2;0/Request;2;0/InvoiceDetailRequest;2;0/InvoiceDetailRequestHeader;2;0/@invoiceDate;1;0" TO="/invoiceDate;1;0">
</MAPCOPY>
</MAP>

<MAP MODE="OUTPUT">
  <MAPTARGET>

<Values version="2.0">
  <record name="xml" javaclass="com.wm.util.Values">
    <value name="node_type">record</value>
    <value name="is_public">false</value>
    <value name="field_type">record</value>
    <value name="field_dim">0</value>
    <value name="wrapper_type">IData</value>
    <value name="nillable">true</value>
    <value name="form_qualified">false</value>
    <value name="is_global">false</value>
    <array name="rec_fields" type="record" depth="1">
      <record javaclass="com.wm.util.Values">
        <value name="node_type">record</value>
        <value name="node_comment"></value>
        <record name="node_hints" javaclass="com.wm.util.Values">
          <value name="field_largerEditor">false</value>
          <value name="field_password">false</value>
        </record>
        <value name="is_public">false</value>
        <value name="field_name">INVOIC02</value>
        <value name="field_type">recref</value>
        <value name="field_dim">0</value>
        <value name="nillable">true</value>
        <value name="form_qualified">false</value>
        <value name="is_global">false</value>
        <value name="modifiable">true</value>
        <value name="rec_ref">PKIWmAriba.documents.IDoc:INVOIC02</value>
      </record>
      <record javaclass="com.wm.util.Values">
        <value name="node_type">record</value>
        <value name="node_comment"></value>
        <record name="node_hints" javaclass="com.wm.util.Values">
          <value name="field_largerEditor">false</value>
          <value name="field_password">false</value>
        </record>
        <value name="is_public">false</value>
        <value name="field_name">orderRequest</value>
        <value name="field_type">recref</value>
        <value name="field_dim">0</value>
        <value name="wrapper_type">IData</value>
        <value name="nillable">true</value>
        <value name="form_qualified">false</value>
        <value name="is_global">false</value>
        <value name="modifiable">true</value>
        <value name="rec_ref">PKIWmAriba.documents.doc_cXML:cXML</value>
      </record>
      <record javaclass="com.wm.util.Values">
        <value name="node_type">record</value>
        <value name="is_public">false</value>
        <value name="field_name">InvoiceRequest</value>
        <value name="field_type">recref</value>
        <value name="field_dim">0</value>
        <value name="nillable">true</value>
        <value name="form_qualified">false</value>
        <value name="is_global">false</value>
        <value name="modifiable">true</value>
        <value name="rec_ref">cXML.documentType.cXML.v1_2_039.invoice.doc_cXML_Invoice:doc_cXML_Invoice</value>
      </record>
      <record javaclass="com.wm.util.Values">
        <value name="node_type">unknown</value>
        <value name="is_public">false</value>
        <value name="field_name">Currency</value>
        <value name="field_type">string</value>
        <value name="field_dim">0</value>
        <value name="nillable">true</value>
        <value name="form_qualified">false</value>
        <value name="is_global">false</value>
      </record>
      <record javaclass="com.wm.util.Values">
        <value name="node_type">unknown</value>
        <value name="is_public">false</value>
        <value name="field_name">CRMemo</value>
        <value name="field_type">string</value>
        <value name="field_dim">0</value>
        <value name="nillable">true</value>
        <value name="form_qualified">false</value>
        <value name="is_global">false</value>
      </record>
      <record javaclass="com.wm.util.Values">
        <value name="node_type">record</value>
        <value name="node_comment"></value>
        <record name="node_hints" javaclass="com.wm.util.Values">
          <value name="field_largerEditor">false</value>
          <value name="field_password">false</value>
        </record>
        <value name="is_public">false</value>
        <value name="field_name">InvoiceDetailItem</value>
        <value name="field_type">recref</value>
        <value name="field_dim">1</value>
        <value name="nillable">true</value>
        <value name="form_qualified">false</value>
        <value name="is_global">false</value>
        <value name="is_soap_array_encoding_used">false</value>
        <value name="rec_closed">true</value>
        <value name="modifiable">true</value>
        <value name="rec_ref">cXML.documentType.cXML.v1_2_039.invoice:docType_InvoiceDetailItem</value>
      </record>
      <record javaclass="com.wm.util.Values">
        <value name="node_type">unknown</value>
        <value name="node_comment"></value>
        <record name="node_hints" javaclass="com.wm.util.Values">
          <value name="field_usereditable">true</value>
          <value name="field_largerEditor">false</value>
          <value name="field_password">false</value>
        </record>
        <value name="is_public">false</value>
        <value name="field_name">totalShippingCost</value>
        <value name="field_type">string</value>
        <value name="field_dim">0</value>
        <array name="field_options" type="value" depth="1">
        </array>
        <value name="nillable">true</value>
        <value name="form_qualified">false</value>
        <value name="is_global">false</value>
      </record>
      <record javaclass="com.wm.util.Values">
        <value name="node_type">unknown</value>
        <value name="node_comment"></value>
        <record name="node_hints" javaclass="com.wm.util.Values">
          <value name="field_usereditable">true</value>
          <value name="field_largerEditor">false</value>
          <value name="field_password">false</value>
        </record>
        <value name="is_public">false</value>
        <value name="field_name">totalTaxableAmount</value>
        <value name="field_type">string</value>
        <value name="field_dim">0</value>
        <array name="field_options" type="value" depth="1">
        </array>
        <value name="nillable">true</value>
        <value name="form_qualified">false</value>
        <value name="is_global">false</value>
      </record>
    </array>
    <value name="modifiable">true</value>
  </record>
</Values>
</MAPTARGET>
  <MAPSOURCE>

<Values version="2.0">
  <record name="xml" javaclass="com.wm.util.Values">
    <value name="node_type">record</value>
    <value name="is_public">false</value>
    <value name="field_type">record</value>
    <value name="field_dim">0</value>
    <value name="wrapper_type">IData</value>
    <value name="nillable">true</value>
    <value name="form_qualified">false</value>
    <value name="is_global">false</value>
    <array name="rec_fields" type="record" depth="1">
      <record javaclass="com.wm.util.Values">
        <value name="node_type">record</value>
        <value name="node_comment"></value>
        <record name="node_hints" javaclass="com.wm.util.Values">
          <value name="field_largerEditor">false</value>
          <value name="field_password">false</value>
        </record>
        <value name="is_public">false</value>
        <value name="field_name">InvoiceDetailItem</value>
        <value name="field_type">recref</value>
        <value name="field_dim">1</value>
        <value name="nillable">true</value>
        <value name="form_qualified">false</value>
        <value name="is_global">false</value>
        <value name="is_soap_array_encoding_used">false</value>
        <value name="rec_closed">true</value>
        <value name="modifiable">true</value>
        <value name="rec_ref">cXML.documentType.cXML.v1_2_039.invoice:docType_InvoiceDetailItem</value>
      </record>
      <record javaclass="com.wm.util.Values">
        <value name="node_type">unknown</value>
        <value name="node_comment"></value>
        <record name="node_hints" javaclass="com.wm.util.Values">
          <value name="field_usereditable">true</value>
          <value name="field_largerEditor">false</value>
          <value name="field_password">false</value>
        </record>
        <value name="is_public">false</value>
        <value name="field_name">totalShippingCost</value>
        <value name="field_type">string</value>
        <value name="field_dim">0</value>
        <array name="field_options" type="value" depth="1">
        </array>
        <value name="nillable">true</value>
        <value name="form_qualified">false</value>
        <value name="is_global">false</value>
      </record>
      <record javaclass="com.wm.util.Values">
        <value name="node_type">unknown</value>
        <value name="node_comment"></value>
        <record name="node_hints" javaclass="com.wm.util.Values">
          <value name="field_usereditable">true</value>
          <value name="field_largerEditor">false</value>
          <value name="field_password">false</value>
        </record>
        <value name="is_public">false</value>
        <value name="field_name">totalTaxableAmount</value>
        <value name="field_type">string</value>
        <value name="field_dim">0</value>
        <array name="field_options" type="value" depth="1">
        </array>
        <value name="nillable">true</value>
        <value name="form_qualified">false</value>
        <value name="is_global">false</value>
      </record>
    </array>
    <value name="modifiable">true</value>
  </record>
</Values>
</MAPSOURCE>

  <!-- nodes -->

<MAPCOPY FROM="/InvoiceDetailItem;4;1;cXML.documentType.cXML.v1_2_039.invoice:docType_InvoiceDetailItem" TO="/InvoiceRequest;4;0;cXML.documentType.cXML.v1_2_039.invoice.doc_cXML_Invoice:doc_cXML_Invoice/cXML;2;0/Request;2;0/InvoiceDetailRequest;2;0/InvoiceDetailOrder;2;1/InvoiceDetailItem;2;1">
</MAPCOPY>

<MAPDELETE FIELD="/InvoiceDetailItem;4;1;cXML.documentType.cXML.v1_2_039.invoice:docType_InvoiceDetailItem">
</MAPDELETE>
</MAP>
</INVOKE>

<INVOKE TIMEOUT="" SERVICE="cXML.invoice:mapInvoiceSummary" VALIDATE-IN="$none" VALIDATE-OUT="$none">
  <COMMENT>Invoice Summary Mapping</COMMENT>

  <!-- nodes -->

<MAP MODE="INPUT">
</MAP>

<MAP MODE="OUTPUT">
  <MAPTARGET>

<Values version="2.0">
  <record name="xml" javaclass="com.wm.util.Values">
    <value name="node_type">record</value>
    <value name="is_public">false</value>
    <value name="field_type">record</value>
    <value name="field_dim">0</value>
    <value name="wrapper_type">IData</value>
    <value name="nillable">true</value>
    <value name="form_qualified">false</value>
    <value name="is_global">false</value>
    <array name="rec_fields" type="record" depth="1">
      <record javaclass="com.wm.util.Values">
        <value name="node_type">unknown</value>
        <value name="is_public">false</value>
        <value name="field_name">fileName</value>
        <value name="field_type">string</value>
        <value name="field_dim">0</value>
        <value name="nillable">true</value>
        <value name="form_qualified">false</value>
        <value name="is_global">false</value>
      </record>
      <record javaclass="com.wm.util.Values">
        <value name="node_type">record</value>
        <value name="node_comment"></value>
        <record name="node_hints" javaclass="com.wm.util.Values">
          <value name="field_largerEditor">false</value>
          <value name="field_password">false</value>
        </record>
        <value name="is_public">false</value>
        <value name="field_name">INVOIC02</value>
        <value name="field_type">recref</value>
        <value name="field_dim">0</value>
        <value name="nillable">true</value>
        <value name="form_qualified">false</value>
        <value name="is_global">false</value>
        <value name="modifiable">true</value>
        <value name="rec_ref">PKIWmAriba.documents.IDoc:INVOIC02</value>
      </record>
      <record javaclass="com.wm.util.Values">
        <value name="node_type">record</value>
        <value name="node_comment"></value>
        <record name="node_hints" javaclass="com.wm.util.Values">
          <value name="field_largerEditor">false</value>
          <value name="field_password">false</value>
        </record>
        <value name="is_public">false</value>
        <value name="field_name">orderRequest</value>
        <value name="field_type">recref</value>
        <value name="field_dim">0</value>
        <value name="wrapper_type">IData</value>
        <value name="nillable">true</value>
        <value name="form_qualified">false</value>
        <value name="is_global">false</value>
        <value name="modifiable">true</value>
        <value name="rec_ref">PKIWmAriba.documents.doc_cXML:cXML</value>
      </record>
      <record javaclass="com.wm.util.Values">
        <value name="node_type">record</value>
        <value name="is_public">false</value>
        <value name="field_name">InvoiceRequest</value>
        <value name="field_type">recref</value>
        <value name="field_dim">0</value>
        <value name="nillable">true</value>
        <value name="form_qualified">false</value>
        <value name="is_global">false</value>
        <value name="modifiable">true</value>
        <value name="rec_ref">cXML.documentType.cXML.v1_2_039.invoice.doc_cXML_Invoice:doc_cXML_Invoice</value>
      </record>
      <record javaclass="com.wm.util.Values">
        <value name="node_type">unknown</value>
        <value name="is_public">false</value>
        <value name="field_name">invoiceDate</value>
        <value name="field_type">string</value>
        <value name="field_dim">0</value>
        <value name="nillable">true</value>
        <value name="form_qualified">false</value>
        <value name="is_global">false</value>
      </record>
      <record javaclass="com.wm.util.Values">
        <value name="node_type">unknown</value>
        <value name="is_public">false</value>
        <value name="field_name">CRMemo</value>
        <value name="field_type">string</value>
        <value name="field_dim">0</value>
        <value name="nillable">true</value>
        <value name="form_qualified">false</value>
        <value name="is_global">false</value>
      </record>
      <record javaclass="com.wm.util.Values">
        <value name="node_type">unknown</value>
        <value name="is_public">false</value>
        <value name="field_name">Currency</value>
        <value name="field_type">string</value>
        <value name="field_dim">0</value>
        <value name="nillable">true</value>
        <value name="form_qualified">false</value>
        <value name="is_global">false</value>
      </record>
      <record javaclass="com.wm.util.Values">
        <value name="node_type">unknown</value>
        <value name="node_comment"></value>
        <record name="node_hints" javaclass="com.wm.util.Values">
          <value name="field_usereditable">true</value>
          <value name="field_largerEditor">false</value>
          <value name="field_password">false</value>
        </record>
        <value name="is_public">false</value>
        <value name="field_name">totalShippingCost</value>
        <value name="field_type">string</value>
        <value name="field_dim">0</value>
        <array name="field_options" type="value" depth="1">
        </array>
        <value name="nillable">true</value>
        <value name="form_qualified">false</value>
        <value name="is_global">false</value>
      </record>
      <record javaclass="com.wm.util.Values">
        <value name="node_type">unknown</value>
        <value name="node_comment"></value>
        <record name="node_hints" javaclass="com.wm.util.Values">
          <value name="field_usereditable">true</value>
          <value name="field_largerEditor">false</value>
          <value name="field_password">false</value>
        </record>
        <value name="is_public">false</value>
        <value name="field_name">totalTaxableAmount</value>
        <value name="field_type">string</value>
        <value name="field_dim">0</value>
        <array name="field_options" type="value" depth="1">
        </array>
        <value name="nillable">true</value>
        <value name="form_qualified">false</value>
        <value name="is_global">false</value>
      </record>
      <record javaclass="com.wm.util.Values">
        <value name="node_type">record</value>
        <value name="node_comment"></value>
        <record name="node_hints" javaclass="com.wm.util.Values">
          <value name="field_largerEditor">false</value>
          <value name="field_password">false</value>
        </record>
        <value name="is_public">false</value>
        <value name="field_name">InvoiceDetailSummary</value>
        <value name="field_type">recref</value>
        <value name="field_dim">0</value>
        <value name="nillable">true</value>
        <value name="form_qualified">false</value>
        <value name="is_global">false</value>
        <value name="rec_closed">true</value>
        <value name="modifiable">true</value>
        <value name="rec_ref">cXML.documentType.cXML.v1_2_039.invoice:docType_InvoiceDetailSummary</value>
      </record>
      <record javaclass="com.wm.util.Values">
        <value name="node_type">record</value>
        <value name="node_comment"></value>
        <record name="node_hints" javaclass="com.wm.util.Values">
          <value name="field_largerEditor">false</value>
          <value name="field_password">false</value>
        </record>
        <value name="is_public">false</value>
        <value name="field_name">Modification_Single</value>
        <value name="field_type">recref</value>
        <value name="field_dim">0</value>
        <value name="nillable">false</value>
        <value name="form_qualified">false</value>
        <value name="is_global">false</value>
        <value name="rec_closed">true</value>
        <value name="modifiable">true</value>
        <value name="rec_ref">cXML.documentType.cXML.v1_2_039.invoice.doc_cXML_Invoice:docType_Modification</value>
      </record>
    </array>
    <value name="modifiable">true</value>
  </record>
</Values>
</MAPTARGET>
  <MAPSOURCE>

<Values version="2.0">
  <record name="xml" javaclass="com.wm.util.Values">
    <value name="node_type">record</value>
    <value name="is_public">false</value>
    <value name="field_type">record</value>
    <value name="field_dim">0</value>
    <value name="wrapper_type">IData</value>
    <value name="nillable">true</value>
    <value name="form_qualified">false</value>
    <value name="is_global">false</value>
    <array name="rec_fields" type="record" depth="1">
      <record javaclass="com.wm.util.Values">
        <value name="node_type">record</value>
        <value name="node_comment"></value>
        <record name="node_hints" javaclass="com.wm.util.Values">
          <value name="field_largerEditor">false</value>
          <value name="field_password">false</value>
        </record>
        <value name="is_public">false</value>
        <value name="field_name">InvoiceDetailSummary</value>
        <value name="field_type">recref</value>
        <value name="field_dim">0</value>
        <value name="nillable">true</value>
        <value name="form_qualified">false</value>
        <value name="is_global">false</value>
        <value name="rec_closed">true</value>
        <value name="modifiable">true</value>
        <value name="rec_ref">cXML.documentType.cXML.v1_2_039.invoice:docType_InvoiceDetailSummary</value>
      </record>
      <record javaclass="com.wm.util.Values">
        <value name="node_type">record</value>
        <value name="node_comment"></value>
        <record name="node_hints" javaclass="com.wm.util.Values">
          <value name="field_largerEditor">false</value>
          <value name="field_password">false</value>
        </record>
        <value name="is_public">false</value>
        <value name="field_name">Modification_Single</value>
        <value name="field_type">recref</value>
        <value name="field_dim">0</value>
        <value name="nillable">false</value>
        <value name="form_qualified">false</value>
        <value name="is_global">false</value>
        <value name="rec_closed">true</value>
        <value name="modifiable">true</value>
        <value name="rec_ref">cXML.documentType.cXML.v1_2_039.invoice.doc_cXML_Invoice:docType_Modification</value>
      </record>
    </array>
    <value name="modifiable">true</value>
  </record>
</Values>
</MAPSOURCE>

  <!-- nodes -->

<MAPCOPY FROM="/InvoiceDetailSummary;4;0;cXML.documentType.cXML.v1_2_039.invoice:docType_InvoiceDetailSummary" TO="/InvoiceRequest;4;0;cXML.documentType.cXML.v1_2_039.invoice.doc_cXML_Invoice:doc_cXML_Invoice/cXML;2;0/Request;2;0/InvoiceDetailRequest;2;0/InvoiceDetailSummary;2;0">
</MAPCOPY>

<MAPDELETE FIELD="/InvoiceDetailSummary;4;0;cXML.documentType.cXML.v1_2_039.invoice:docType_InvoiceDetailSummary">
</MAPDELETE>

<MAPDELETE FIELD="/CRMemo;1;0">
</MAPDELETE>

<MAPDELETE FIELD="/Currency;1;0">
</MAPDELETE>

<MAPDELETE FIELD="/orderRequest;4;0;PKIWmAriba.documents.doc_cXML:cXML">
</MAPDELETE>

<MAPDELETE FIELD="/INVOIC02;4;0;PKIWmAriba.documents.IDoc:INVOIC02">
</MAPDELETE>

<MAPDELETE FIELD="/totalShippingCost;1;0">
</MAPDELETE>

<MAPDELETE FIELD="/totalTaxableAmount;1;0">
</MAPDELETE>
</MAP>
</INVOKE>

<INVOKE TIMEOUT="" SERVICE="pub.flow:clearPipeline" VALIDATE-IN="$none" VALIDATE-OUT="$none">
  <COMMENT>only preserve InvoiceRequest</COMMENT>

  <!-- nodes -->

<MAP MODE="INPUT">
  <MAPTARGET>

<Values version="2.0">
  <record name="xml" javaclass="com.wm.util.Values">
    <value name="node_type">record</value>
    <value name="is_public">false</value>
    <value name="field_name">clearPipelineInput</value>
    <value name="field_type">record</value>
    <value name="field_dim">0</value>
    <value name="wrapper_type">IData</value>
    <value name="nillable">true</value>
    <value name="form_qualified">false</value>
    <value name="is_global">false</value>
    <array name="rec_fields" type="record" depth="1">
      <record javaclass="com.wm.util.Values">
        <value name="node_type">unknown</value>
        <value name="is_public">false</value>
        <value name="field_name">preserve</value>
        <value name="field_type">string</value>
        <value name="field_dim">1</value>
        <value name="field_opt">true</value>
        <value name="nillable">true</value>
        <value name="form_qualified">false</value>
        <value name="is_global">false</value>
        <value name="is_soap_array_encoding_used">false</value>
      </record>
    </array>
    <value name="modifiable">true</value>
  </record>
</Values>
</MAPTARGET>
  <MAPSOURCE>

<Values version="2.0">
  <record name="xml" javaclass="com.wm.util.Values">
    <value name="node_type">record</value>
    <value name="is_public">false</value>
    <value name="field_type">record</value>
    <value name="field_dim">0</value>
    <value name="wrapper_type">IData</value>
    <value name="nillable">true</value>
    <value name="form_qualified">false</value>
    <value name="is_global">false</value>
    <array name="rec_fields" type="record" depth="1">
    </array>
    <value name="modifiable">true</value>
  </record>
</Values>
</MAPSOURCE>

  <!-- nodes -->

<MAPSET NAME="Setter" OVERWRITE="true" VARIABLES="false" GLOBALVARIABLES="false" FIELD="/preserve;1;1">
  <DATA ENCODING="XMLValues" I18N="true">

<Values version="2.0">
  <array name="xml" type="value" depth="1">
    <value>InvoiceRequest</value>
  </array>
  <record name="type" javaclass="com.wm.util.Values">
    <value name="node_type">unknown</value>
    <value name="is_public">false</value>
    <value name="field_name">preserve</value>
    <value name="field_type">string</value>
    <value name="field_dim">1</value>
    <value name="field_opt">true</value>
    <value name="nillable">true</value>
    <value name="form_qualified">false</value>
    <value name="is_global">false</value>
    <value name="is_soap_array_encoding_used">false</value>
  </record>
</Values>
</DATA>
</MAPSET>
</MAP>
</INVOKE>
</FLOW>
